{
  "homebrew_version": "4.4.21-62-g27a9032",
  "used_options": [

  ],
  "unused_options": [

  ],
  "built_as_bottle": true,
  "poured_from_bottle": true,
  "loaded_from_api": true,
  "installed_as_dependency": true,
  "installed_on_request": true,
  "changed_files": [
    "lib/pkgconfig/libzstd.pc"
  ],
  "time": 1741198360,
  "source_modified_time": 1739923464,
  "compiler": "clang",
  "aliases": [
    "pzstd"
  ],
  "runtime_dependencies": [
    {
      "full_name": "lz4",
      "version": "1.10.0",
      "revision": 0,
      "pkg_version": "1.10.0",
      "declared_directly": true
    },
    {
      "full_name": "xz",
      "version": "5.6.4",
      "revision": 0,
      "pkg_version": "5.6.4",
      "declared_directly": true
    }
  ],
  "source": {
    "spec": "stable",
    "versions": {
      "stable": "1.5.7",
      "head": null,
      "version_scheme": 0
    },
    "path": "/Users/van/Library/Caches/Homebrew/api/formula.jws.json",
    "tap_git_head": "056318f4642987c0b8cac201a20740d5013961c7",
    "tap": "homebrew/core"
  },
  "arch": "arm64",
  "built_on": {
    "os": "Macintosh",
    "os_version": "macOS 15",
    "cpu_family": "dunno",
    "xcode": "16.2",
    "clt": "16.2.0.0.1.1733547573",
    "preferred_perl": "5.34"
  }
}